opentelemetry/exporter/otlp/proto/http/sigv4/__init__.py
opentelemetry/exporter/otlp/proto/http/sigv4/exporter.py
otel_sigv4_exporter-0.1.0.dist-info/METADATA
otel_sigv4_exporter-0.1.0.dist-info/WHEEL
otel_sigv4_exporter-0.1.0.dist-info/top_level.txt
otel_sigv4_exporter-0.1.0.dist-info/RECORD
